[
    {
        "category": "Powerup",
        "id": "b51925f1-cb16-455b-ad89-68a93e3f06ec",
        "name": "Active Camo I",
        "description": "Active Camo creates a refractive field that provides optical masking. Quick movements and offensive actions destabilize the effect. Short duration.",
        "price": 75,
        "isWearable": false,
        "subCategory": "Equipment",
        "wearableId": 0,
        "isDurable": false,
        "rarity": "Uncommon",
        "rarityType": 1,
        "energyLevel": 4,
        "imageUrl": "https://image.halocdn.com/h5/requisitions/b51925f1-cb16-455b-ad89-68a93e3f06ec?locale=en&width=200&hash=rETD9hzqObeyJTsCM1uigLQcZS1C7%2b7SAwxftt%2bpG1U%3d"
    },
    {
        "category": "Powerup",
        "id": "665a7c65-25a8-4c0d-8e78-249bc0734bd3",
        "name": "Active Camo II",
        "description": "Active Camo creates a refractive field that provides optical masking. Quick movements and offensive actions destabilize the effect. Medium duration.",
        "price": 100,
        "isWearable": false,
        "subCategory": "Equipment",
        "wearableId": 0,
        "isDurable": false,
        "rarity": "Rare",
        "rarityType": 2,
        "energyLevel": 4,
        "imageUrl": "https://image.halocdn.com/h5/requisitions/665a7c65-25a8-4c0d-8e78-249bc0734bd3?locale=en&width=200&hash=M180QeG6UcapWe5gVrywRseY0RqTQfZ8wVESxS1G%2fxg%3d"
    },
    {
        "category": "Powerup",
        "id": "f1568c0a-68e7-49e3-8799-8efe53fd38f0",
        "name": "Active Camo III",
        "description": "Active Camo creates a refractive field that provides optical masking. Quick movements and offensive actions destabilize the effect. Long duration.",
        "price": 150,
        "isWearable": false,
        "subCategory": "Equipment",
        "wearableId": 0,
        "isDurable": false,
        "rarity": "Ultra Rare",
        "rarityType": 3,
        "energyLevel": 5,
        "imageUrl": "https://image.halocdn.com/h5/requisitions/f1568c0a-68e7-49e3-8799-8efe53fd38f0?locale=en&width=200&hash=MEO5E0jNdazZwjJDSa96QXO1rrKxRYnJXtDsMdNcuXI%3d"
    },
    {
        "category": "Powerup",
        "id": "adf41201-4940-4055-8e66-dc181014edf2",
        "name": "Damage Boost I",
        "description": "Damage Boost significantly increases the user's weapon, grenade, and vehicle damage for a short time. The Damage Boost also reduces visibility. Short duration.",
        "price": 100,
        "isWearable": false,
        "subCategory": "Equipment",
        "wearableId": 0,
        "isDurable": false,
        "rarity": "Rare",
        "rarityType": 2,
        "energyLevel": 5,
        "imageUrl": "https://image.halocdn.com/h5/requisitions/adf41201-4940-4055-8e66-dc181014edf2?locale=en&width=200&hash=b4FCloEhwO1N3p4QIVhAQtnFz%2b5JqgKf6uCHPVOTEVk%3d"
    },
    {
        "category": "Powerup",
        "id": "cf9ce92d-6a24-432c-b2aa-d103d3d705de",
        "name": "Damage Boost II",
        "description": "Damage Boost significantly increases the user's weapon, grenade, and vehicle damage for a short time. The Damage Boost also reduces visibility. Medium duration.",
        "price": 150,
        "isWearable": false,
        "subCategory": "Equipment",
        "wearableId": 0,
        "isDurable": false,
        "rarity": "Ultra Rare",
        "rarityType": 3,
        "energyLevel": 5,
        "imageUrl": "https://image.halocdn.com/h5/requisitions/cf9ce92d-6a24-432c-b2aa-d103d3d705de?locale=en&width=200&hash=bwcOTUwIsLKnI14zQyUcB%2ba0RWBMRVKu%2b1i9X4NdZQs%3d"
    },
    {
        "category": "Powerup",
        "id": "7abbef0c-5cac-4d5d-af94-69490b5cb881",
        "name": "Damage Boost III",
        "description": "Damage Boost significantly increases the user's weapon, grenade, and vehicle damage for a short time. The Damage Boost also reduces visibility. Long duration.",
        "price": 200,
        "isWearable": false,
        "subCategory": "Equipment",
        "wearableId": 0,
        "isDurable": false,
        "rarity": "Legendary",
        "rarityType": 4,
        "energyLevel": 6,
        "imageUrl": "https://image.halocdn.com/h5/requisitions/7abbef0c-5cac-4d5d-af94-69490b5cb881?locale=en&width=200&hash=NJARiaFo3dFrIv02gsVHONo1kojR6ugxnR%2f%2bbxHpaHY%3d"
    },
    {
        "category": "Powerup",
        "id": "aedd49cd-987b-45c8-aeb7-2b6bc75594f7",
        "name": "Overshield I",
        "description": "Overshield adds an extra layer of shields that do not regenerate. This extra layer is displayed in green on the HUD's shield indicator. Short duration.",
        "price": 75,
        "isWearable": false,
        "subCategory": "Equipment",
        "wearableId": 0,
        "isDurable": false,
        "rarity": "Uncommon",
        "rarityType": 1,
        "energyLevel": 3,
        "imageUrl": "https://image.halocdn.com/h5/requisitions/aedd49cd-987b-45c8-aeb7-2b6bc75594f7?locale=en&width=200&hash=aJEcMkkJmKwxsy1QbItfOyJwWnQy92GoRDP70QWegrk%3d"
    },
    {
        "category": "Powerup",
        "id": "255409ee-c701-4d35-a480-e4d0475fc7d5",
        "name": "Overshield II",
        "description": "Overshield adds an extra layer of shields that do not regenerate. This extra layer is displayed in green on the HUD's shield indicator. Medium duration.",
        "price": 100,
        "isWearable": false,
        "subCategory": "Equipment",
        "wearableId": 0,
        "isDurable": false,
        "rarity": "Rare",
        "rarityType": 2,
        "energyLevel": 3,
        "imageUrl": "https://image.halocdn.com/h5/requisitions/255409ee-c701-4d35-a480-e4d0475fc7d5?locale=en&width=200&hash=IsBOi6f7UiXcQzKtmeLa3VaZB4yiuvBhCjaBfbs99GU%3d"
    },
    {
        "category": "Powerup",
        "id": "c2783c51-04c6-49b1-b9b1-928d507c6a7b",
        "name": "Overshield III",
        "description": "Overshield adds an extra layer of shields that do not regenerate. This extra layer is displayed in green on the HUD's shield indicator. Long duration.",
        "price": 150,
        "isWearable": false,
        "subCategory": "Equipment",
        "wearableId": 0,
        "isDurable": false,
        "rarity": "Ultra Rare",
        "rarityType": 3,
        "energyLevel": 4,
        "imageUrl": "https://image.halocdn.com/h5/requisitions/c2783c51-04c6-49b1-b9b1-928d507c6a7b?locale=en&width=200&hash=f%2bTXXhqrObVcb06Mr3yhB4N%2fd%2f4n91FdrwlRoEI3Mxg%3d"
    },
    {
        "category": "Powerup",
        "id": "83be2d7c-0bb8-4398-8dae-51319d6f7a64",
        "name": "Speed Boost I",
        "description": "Speed Boost temporarily increases movement, reloading, assassination, and weapon switch speed. Short duration.",
        "price": 50,
        "isWearable": false,
        "subCategory": "Equipment",
        "wearableId": 0,
        "isDurable": false,
        "rarity": "Common",
        "rarityType": 0,
        "energyLevel": 2,
        "imageUrl": "https://image.halocdn.com/h5/requisitions/83be2d7c-0bb8-4398-8dae-51319d6f7a64?locale=en&width=200&hash=Y0z7pbVjXRAlzdsarLNhPIf6sUG6xeTn0EUCJuKhVDo%3d"
    },
    {
        "category": "Powerup",
        "id": "7c573420-2a31-4162-81e5-b4734e642159",
        "name": "Speed Boost II",
        "description": "Speed Boost temporarily increases movement, reloading, assassination, and weapon switch speed. Medium duration.",
        "price": 75,
        "isWearable": false,
        "subCategory": "Equipment",
        "wearableId": 0,
        "isDurable": false,
        "rarity": "Uncommon",
        "rarityType": 1,
        "energyLevel": 2,
        "imageUrl": "https://image.halocdn.com/h5/requisitions/7c573420-2a31-4162-81e5-b4734e642159?locale=en&width=200&hash=JX9qxklK0jDBByq7dUx%2fB2sFrhLXecLWbL7p1u8D0r8%3d"
    },
    {
        "category": "Powerup",
        "id": "4003cfdb-2048-4f14-a2cc-acfe22c4f652",
        "name": "Speed Boost III",
        "description": "Speed Boost temporarily increases movement, reloading, assassination, and weapon switch speed. Long duration.",
        "price": 100,
        "isWearable": false,
        "subCategory": "Equipment",
        "wearableId": 0,
        "isDurable": false,
        "rarity": "Rare",
        "rarityType": 2,
        "energyLevel": 3,
        "imageUrl": "https://image.halocdn.com/h5/requisitions/4003cfdb-2048-4f14-a2cc-acfe22c4f652?locale=en&width=200&hash=ttKCrGnLC8SRPJreQMJy2ivl%2bb8EUGnzRMlyDHp%2fCag%3d"
    }
]